ccRender-0.11.1a2.dist-info/DESCRIPTION.rst
ccRender-0.11.1a2.dist-info/METADATA
ccRender-0.11.1a2.dist-info/RECORD
ccRender-0.11.1a2.dist-info/WHEEL
ccRender-0.11.1a2.dist-info/metadata.json
ccRender-0.11.1a2.dist-info/top_level.txt
ccrender/__init__.py
ccrender/ccSimple.py
