Metadata-Version: 2.0
Name: ccRender
Version: 0.11.1a2
Summary: Cloud-based Blender rendering addon
Home-page: https://github.com/omnibond/ccRender
Author: Cliffton Hicks
Author-email: cliffton@omnibond.com
License: LGPL
Platform: UNKNOWN
Classifier: Development Status :: 3 - Alpha
Classifier: Programming Language :: Python
Classifier: Programming Language :: Python :: 3
Classifier: Programming Language :: Python :: 3.4
Classifier: Programming Language :: Python :: 3.5
Requires-Dist: pyperclip
Requires-Dist: scp
